{
  "type": "BREAKOUT",
  "currency": "BTC",
  "symbol": "BTCUSD",
  "klines": {
    "period": 60,
    "symbol": "BTCUSD"
  },
  "breakout": {
    "area_width": 100
  },
  "conditions": {
    "enter": [
      {
        "id": 1,
        "action": "ENTER_LONG",
        "confidence": 10,
        "params": [
          ["EMA_50", "EMA_100", ">"],
          ["STOCHk_5_3_3", "STOCHd_5_3_3", ">"],
          ["STOCHk_5_3_3", 20, "<"],
          ["STOCHd_5_3_3", 20, "<"],
          ["RSI_6", 33, "<"],
          ["STDEV_6", 500000, "<"]
        ]
      }
    ],
    "exit": {
      "action": "EXIT",
      "stop_loss": -0.005,
      "take_profit": 0.01,
      "indicators": [
        {
          "key": "RSI_6",
          "short_exit_limit": [33, "<"],
          "long_exit_limit": [67, ">"]
        }
      ]
    }
  },
  "order_params": {
    "entry": {
      "ord_type": "Limit",
      "limit_margin_ep": 5000,
      "wallet_ratio": 0.1,
      "safety_tp": 0.05,
      "safety_sl": 0.02
    },
    "exit": {
      "ord_type": "Limit",
      "limit_margin_ep": 5000
    }
  }
}